Metadata-Version: 1.2
Name: django-pika-pubsub
Version: 0.1
Summary: A Django app to publish and consume rmq-messages via Pika.
Home-page: https://grafia.ink/
Author: Bogdanov Dmitry
Author-email: bogdanov@phie.ru
License: UNKNOWN
Platform: UNKNOWN
Classifier: Framework :: Django
Classifier: Framework :: Django :: 2.0
Classifier: Framework :: Django :: 2.1
Classifier: Framework :: Django :: 2.2
Classifier: Framework :: Django :: 3.0
Classifier: Intended Audience :: Developers
Classifier: Operating System :: OS Independent
Classifier: Programming Language :: Python
Classifier: Programming Language :: Python :: 3
Classifier: Programming Language :: Python :: 3.5
Classifier: Programming Language :: Python :: 3.6
Classifier: Programming Language :: Python :: 3.7
Classifier: Programming Language :: Python :: 3 :: Only
Classifier: Topic :: Software Development
Requires-Python: >=3.5
